mayacal/__init__.py
mayacal/utils/calendar_round.py
mayacal/utils/haab.py
mayacal/utils/long_count.py
mayacal/utils/mayadate.py
mayacal/utils/tzolkin.py
mayacal/utils/utils.py
mayacal-0.2.4a0.dist-info/LICENSE.txt
mayacal-0.2.4a0.dist-info/METADATA
mayacal-0.2.4a0.dist-info/WHEEL
mayacal-0.2.4a0.dist-info/top_level.txt
mayacal-0.2.4a0.dist-info/RECORD
