Metadata-Version: 2.1
Name: mayacal
Version: 0.2.4a0
Summary: Basic calendar functions for the classical Mayan calendar
Home-page: https://github.com/jonbleiberg88/mayacal
Author: Jon Bleiberg
Author-email: 
License: MIT
Keywords: Maya,Mayan,Calendar,Classical,Ancient
Platform: UNKNOWN
Classifier: Development Status :: 3 - Alpha
Classifier: License :: OSI Approved :: MIT License
Classifier: Programming Language :: Python :: 3
Requires-Python: >=3.5
